matrix_content_scanner/__init__.py
matrix_content_scanner/config.py
matrix_content_scanner/httpserver.py
matrix_content_scanner/logutils.py
matrix_content_scanner/mcs.py
matrix_content_scanner/mcs_rust/__init__.pyi
matrix_content_scanner/mcs_rust/crypto.pyi
matrix_content_scanner/py.typed
matrix_content_scanner/scanner/__init__.py
matrix_content_scanner/scanner/file_downloader.py
matrix_content_scanner/scanner/scanner.py
matrix_content_scanner/servlets/__init__.py
matrix_content_scanner/servlets/download.py
matrix_content_scanner/servlets/public_key.py
matrix_content_scanner/servlets/scan.py
matrix_content_scanner/servlets/thumbnail.py
matrix_content_scanner/utils/__init__.py
matrix_content_scanner/utils/constants.py
matrix_content_scanner/utils/encrypted_file_metadata.py
matrix_content_scanner/utils/errors.py
matrix_content_scanner/utils/rust.py
matrix_content_scanner/utils/types.py
matrix_content_scanner/mcs_rust.abi3.so
matrix_content_scanner-1.2.1.dist-info/LICENSE
matrix_content_scanner-1.2.1.dist-info/LICENSE-COMMERCIAL
matrix_content_scanner-1.2.1.dist-info/METADATA
matrix_content_scanner-1.2.1.dist-info/WHEEL
matrix_content_scanner-1.2.1.dist-info/entry_points.txt
matrix_content_scanner-1.2.1.dist-info/RECORD
