Metadata-Version: 2.1
Name: matrix_content_scanner
Version: 1.2.1
Summary: A web service for scanning media hosted by a Matrix media repository
License: AGPL-3.0-only OR LicenseRef-Element-Commercial
Author: Element Backend Team
Author-email: team-backend-synapse@element.io
Requires-Python: >=3.10.0,<4.0.0
Classifier: License :: Other/Proprietary License
Classifier: Programming Language :: Python :: 3
Classifier: Programming Language :: Python :: 3.10
Classifier: Programming Language :: Python :: 3.11
Classifier: Programming Language :: Python :: 3.12
Classifier: Programming Language :: Python :: 3.13
Requires-Dist: aiohttp (>=3.8.0)
Requires-Dist: attrs (>=19.2.0)
Requires-Dist: cachetools (>=5.4.0)
Requires-Dist: canonicaljson (>=1.6.3)
Requires-Dist: humanfriendly (>=10.0)
Requires-Dist: jsonschema (>=4.23.0)
Requires-Dist: python-magic (>=0.4.15,<0.5)
Requires-Dist: pyyaml (>=5.1.1)
Requires-Dist: setuptools_rust (>=1.3)
Project-URL: documentation, https://github.com/element-hq/matrix-content-scanner/blob/main/README.md
Project-URL: homepage, https://github.com/element-hq/matrix-content-scanner
Project-URL: repository, https://github.com/element-hq/matrix-content-scanner.git
